telegram_notifier/__init__.py
telegram_notifier/_version.py
telegram_notifier/bot.py
telegram_notifier/exceptions.py
telegram_notifier/hooks.py
telegram_notifier/plugin.py
telegram_notifier/telegram_manager.py
pytest_telegram_notifier-1.4.0.dist-info/LICENSE.rst
pytest_telegram_notifier-1.4.0.dist-info/METADATA
pytest_telegram_notifier-1.4.0.dist-info/WHEEL
pytest_telegram_notifier-1.4.0.dist-info/entry_points.txt
pytest_telegram_notifier-1.4.0.dist-info/top_level.txt
pytest_telegram_notifier-1.4.0.dist-info/RECORD
