Metadata-Version: 2.1
Name: pytest-telegram-notifier
Version: 1.4.0
Summary: Telegram notification plugin for Pytest
Author-email: Kirill Matveev <matveevkirill@internet.ru>
Maintainer-email: Kirill Matveev <matveevkirill@internet.ru>
License: Apache License
Project-URL: Github, https://github.com/PlagerX-Group/pytest-telegram-notifier
Project-URL: Issues, https://github.com/PlagerX-Group/pytest-telegram-notifier/issues
Keywords: pytest-telegram-notifier
Classifier: Framework :: Pytest
Classifier: Intended Audience :: Developers
Classifier: License :: OSI Approved :: Apache Software License
Classifier: Development Status :: 5 - Production/Stable
Classifier: Operating System :: MacOS
Classifier: Operating System :: Microsoft :: Windows
Classifier: Topic :: Software Development :: Quality Assurance
Classifier: Topic :: Software Development :: Testing
Classifier: Programming Language :: Python :: 3 :: Only
Classifier: Programming Language :: Python :: 3.9
Requires-Python: >=3.9.6
License-File: LICENSE.rst
